{
  "unversionedId": "components/list",
  "id": "components/list",
  "title": "List Style",
  "description": "An item",
  "source": "@site/docs/03-components/list.md",
  "sourceDirName": "03-components",
  "slug": "/components/list",
  "permalink": "/bee-ui/docs/components/list",
  "draft": false,
  "editUrl": "https://github.com/xirosoft/bee-ui/edit/main/docs/03-components/list.md",
  "tags": [],
  "version": "current",
  "lastUpdatedAt": 1675775164,
  "formattedLastUpdatedAt": "Feb 7, 2023",
  "frontMatter": {
    "id": "list",
    "title": "List Style"
  },
  "sidebar": "myAutogeneratedSidebar",
  "previous": {
    "title": "Form",
    "permalink": "/bee-ui/docs/components/form"
  },
  "next": {
    "title": "Pagination",
    "permalink": "/bee-ui/docs/components/pagination"
  }
}