{
  "unversionedId": "components/card/card",
  "id": "components/card/card",
  "title": "card",
  "description": "Card - BeeComp",
  "source": "@site/docs/03-components/card/card.md",
  "sourceDirName": "03-components/card",
  "slug": "/components/card/",
  "permalink": "/bee-ui/docs/components/card/",
  "draft": false,
  "editUrl": "https://github.com/xirosoft/bee-ui-docs/edit/main/docs/03-components/card/card.md",
  "tags": [],
  "version": "current",
  "lastUpdatedAt": 1539502055,
  "formattedLastUpdatedAt": "Oct 14, 2018",
  "frontMatter": {},
  "sidebar": "myAutogeneratedSidebar",
  "previous": {
    "title": "button",
    "permalink": "/bee-ui/docs/components/button"
  },
  "next": {
    "title": "Security",
    "permalink": "/bee-ui/docs/security"
  }
}